{
  "project_info": {
    "project_number": "467533798799",
    "firebase_url": "https://mandi-online-5e4fa-default-rtdb.firebaseio.com",
    "project_id": "mandi-online-5e4fa",
    "storage_bucket": "mandi-online-5e4fa.appspot.com"
  },
  "client": [
    {
      "client_info": {
        "mobilesdk_app_id": "1:467533798799:android:3c1fd330836d45f0d53ffa",
        "android_client_info": {
          "package_name": "com.connect.mandionline"
        }
      },
      "oauth_client": [
        {
          "client_id": "467533798799-vv8ian420jqnfv7vdi3spifrud8h4193.apps.googleusercontent.com",
          "client_type": 3
        }
      ],
      "api_key": [
        {
          "current_key": "AIzaSyDJfTPvj1WRtaevENxuPHUmBXT7GBVgcyY"
        }
      ],
      "services": {
        "appinvite_service": {
          "other_platform_oauth_client": [
            {
              "client_id": "467533798799-vv8ian420jqnfv7vdi3spifrud8h4193.apps.googleusercontent.com",
              "client_type": 3
            }
          ]
        }
      }
    }
  ],
  "configuration_version": "1"
}